fabric/__init__.py
fabric/__main__.py
fabric/_version.py
fabric/auth.py
fabric/config.py
fabric/connection.py
fabric/exceptions.py
fabric/executor.py
fabric/group.py
fabric/main.py
fabric/runners.py
fabric/tasks.py
fabric/transfer.py
fabric/tunnels.py
fabric/util.py
fabric/testing/__init__.py
fabric/testing/base.py
fabric/testing/fixtures.py
fabric-3.2.1.dist-info/LICENSE
fabric-3.2.1.dist-info/METADATA
fabric-3.2.1.dist-info/WHEEL
fabric-3.2.1.dist-info/entry_points.txt
fabric-3.2.1.dist-info/top_level.txt
fabric-3.2.1.dist-info/RECORD
