Metadata-Version: 2.1
Name: fabric
Version: 3.2.1
Summary: High level SSH command execution
Home-page: https://fabfile.org
Author: Jeff Forcier
Author-email: jeff@bitprophet.org
License: BSD
Project-URL: Docs, https://docs.fabfile.org
Project-URL: Source, https://github.com/fabric/fabric
Project-URL: Issues, https://github.com/fabric/fabric/issues
Project-URL: Changelog, https://www.fabfile.org/changelog.html
Project-URL: CI, https://app.circleci.com/pipelines/github/fabric/fabric
Project-URL: Twitter, https://twitter.com/pyfabric
Platform: UNKNOWN
Classifier: Development Status :: 5 - Production/Stable
Classifier: Environment :: Console
Classifier: Intended Audience :: Developers
Classifier: Intended Audience :: System Administrators
Classifier: License :: OSI Approved :: BSD License
Classifier: Operating System :: POSIX
Classifier: Operating System :: Unix
Classifier: Operating System :: MacOS :: MacOS X
Classifier: Operating System :: Microsoft :: Windows
Classifier: Programming Language :: Python
Classifier: Programming Language :: Python :: 3
Classifier: Programming Language :: Python :: 3 :: Only
Classifier: Programming Language :: Python :: 3.6
Classifier: Programming Language :: Python :: 3.7
Classifier: Programming Language :: Python :: 3.8
Classifier: Programming Language :: Python :: 3.9
Classifier: Programming Language :: Python :: 3.10
Classifier: Programming Language :: Python :: 3.11
Classifier: Topic :: Software Development
Classifier: Topic :: Software Development :: Build Tools
Classifier: Topic :: Software Development :: Libraries
Classifier: Topic :: Software Development :: Libraries :: Python Modules
Classifier: Topic :: System :: Clustering
Classifier: Topic :: System :: Software Distribution
Classifier: Topic :: System :: Systems Administration
Provides-Extra: testing
Provides-Extra: pytest
